zipinto.py
zipinto-1.0.0.dist-info/LICENSE
zipinto-1.0.0.dist-info/METADATA
zipinto-1.0.0.dist-info/WHEEL
zipinto-1.0.0.dist-info/top_level.txt
zipinto-1.0.0.dist-info/RECORD
