Metadata-Version: 2.1
Name: zipinto
Version: 1.0.0
Summary: Some operations for zip compression files
Author: ChewangNeko
Author-email: 2745283841@qq.com
Classifier: Programming Language :: Python :: 3
Classifier: License :: OSI Approved :: MIT License
Classifier: Operating System :: OS Independent
License-File: LICENSE
